<r:RDF 
xmlns:r="http://www.w3.org/1999/02/22-rdf-syntax-ns#" 
xmlns:s="http://www.w3.org/TR/1999/PR-rdf-schema-19990303#" 
xmlns:n="http://www.nesstar.org/rdf/" 
xmlns:p3="http://www.nesstar.org/rdf/"
xmlns:p1="http://www.nesstar.org/rdf/acu/"
xmlns:p5="http://www.nesstar.org/rdf/hc/"
xmlns:p4="http://www.nesstar.org/rdf/faster/"
xmlns:p2="http://www.nesstar.org/rdf/common/"
xmlns:n43="http://www.nesstar.org/rdf/faster/Variable#"
xmlns:n42="http://www.nesstar.org/rdf/faster/Variable2#"
xmlns:n41="http://www.nesstar.org/rdf/faster/Variable3#"
>


<r:Bag r:about="http://129.177.90.166:80/obj/fSection/IEEP2004_Download_VG1@variables">
<r:_1 r:resource="http://129.177.90.166:80/obj/fVariable/IEEP2004_Download_V1" />
<r:_2 r:resource="http://129.177.90.166:80/obj/fVariable/IEEP2004_Download_V2" />
<r:_3 r:resource="http://129.177.90.166:80/obj/fVariable/IEEP2004_Download_V3" />
<r:_4 r:resource="http://129.177.90.166:80/obj/fVariable/IEEP2004_Download_V4" />
<r:_5 r:resource="http://129.177.90.166:80/obj/fVariable/IEEP2004_Download_V5" />
<r:_6 r:resource="http://129.177.90.166:80/obj/fVariable/IEEP2004_Download_V6" />
<r:_7 r:resource="http://129.177.90.166:80/obj/fVariable/IEEP2004_Download_V7" />
<r:_8 r:resource="http://129.177.90.166:80/obj/fVariable/IEEP2004_Download_V8" />
<r:_9 r:resource="http://129.177.90.166:80/obj/fVariable/IEEP2004_Download_V9" />
<r:_10 r:resource="http://129.177.90.166:80/obj/fVariable/IEEP2004_Download_V10" />
<r:_11 r:resource="http://129.177.90.166:80/obj/fVariable/IEEP2004_Download_V11" />
<r:_12 r:resource="http://129.177.90.166:80/obj/fVariable/IEEP2004_Download_V12" />
</r:Bag>
<p4:Variable3 r:about="http://129.177.90.166:80/obj/fVariable/IEEP2004_Download_V1">
<n:complete>true</n:complete>
<s:label>Constituency</s:label>
<n:creationDate>2009-11-30 16:13:12.0</n:creationDate>
<n:email>false</n:email>
<n43:name>Constituency</n43:name>
<n43:study r:resource="http://129.177.90.166:80/obj/fStudy/IEEP2004_Download" />
<n42:width>10</n42:width>
<n42:numCats>0</n42:numCats>
<n43:isKey>false</n43:isKey>
<n43:isWeight>false</n43:isWeight>
<n43:noInvalidResponses>0</n43:noInvalidResponses>
<n43:intervl>discrete</n43:intervl>
<n43:format>character</n43:format>
<n43:formatSchema>other</n43:formatSchema>
<n43:varID>V1</n43:varID>
<n43:noValidResponses>5</n43:noValidResponses>
<n43:position>1</n43:position>
<n43:sections r:resource="http://129.177.90.166:80/obj/fVariable/IEEP2004_Download_V1@sections" />
<n43:measures r:resource="http://129.177.90.166:80/obj/fVariable/IEEP2004_Download_V1@measures" />
<n43:statistics r:resource="http://129.177.90.166:80/obj/fVariable/IEEP2004_Download_V1@statistics" />
<n43:datafile r:resource="http://129.177.90.166:80/obj/fDatafile/IEEP2004_Download_F1" />
<n43:groups r:resource="http://129.177.90.166:80/obj/fVariable/IEEP2004_Download_V1@groups" />
<n43:factsheets r:resource="http://129.177.90.166:80/obj/fVariable/IEEP2004_Download_V1@factsheets" />
<n43:tables r:resource="http://129.177.90.166:80/obj/fVariable/IEEP2004_Download_V1@tables" />
<n43:weightVariables r:resource="http://129.177.90.166:80/obj/fVariable/IEEP2004_Download_V1@weightVariables" />
<n43:section r:resource="http://129.177.90.166:80/obj/fSection/IEEP2004_Download_VG1" />
</p4:Variable3>
<p4:Variable3 r:about="http://129.177.90.166:80/obj/fVariable/IEEP2004_Download_V2">
<n:complete>true</n:complete>
<s:label>Year</s:label>
<n:creationDate>2009-11-30 16:13:12.0</n:creationDate>
<n:email>false</n:email>
<n43:name>Year</n43:name>
<n43:study r:resource="http://129.177.90.166:80/obj/fStudy/IEEP2004_Download" />
<n42:numCats>0</n42:numCats>
<n43:isKey>false</n43:isKey>
<n43:isWeight>false</n43:isWeight>
<n43:noInvalidResponses>0</n43:noInvalidResponses>
<n43:decimalPlaces>0</n43:decimalPlaces>
<n43:valRangeMax>2004.0</n43:valRangeMax>
<n43:valRangeMin>2004.0</n43:valRangeMin>
<n43:intervl>discrete</n43:intervl>
<n43:format>numeric</n43:format>
<n43:formatSchema>other</n43:formatSchema>
<n43:varID>V2</n43:varID>
<n43:noValidResponses>5</n43:noValidResponses>
<n43:meanValue>2004.0</n43:meanValue>
<n43:maxValue>2004.0</n43:maxValue>
<n43:minValue>2004.0</n43:minValue>
<n43:stdValue>0.0</n43:stdValue>
<n43:position>2</n43:position>
<n43:sections r:resource="http://129.177.90.166:80/obj/fVariable/IEEP2004_Download_V2@sections" />
<n43:measures r:resource="http://129.177.90.166:80/obj/fVariable/IEEP2004_Download_V2@measures" />
<n43:statistics r:resource="http://129.177.90.166:80/obj/fVariable/IEEP2004_Download_V2@statistics" />
<n43:datafile r:resource="http://129.177.90.166:80/obj/fDatafile/IEEP2004_Download_F1" />
<n43:groups r:resource="http://129.177.90.166:80/obj/fVariable/IEEP2004_Download_V2@groups" />
<n43:factsheets r:resource="http://129.177.90.166:80/obj/fVariable/IEEP2004_Download_V2@factsheets" />
<n43:tables r:resource="http://129.177.90.166:80/obj/fVariable/IEEP2004_Download_V2@tables" />
<n43:weightVariables r:resource="http://129.177.90.166:80/obj/fVariable/IEEP2004_Download_V2@weightVariables" />
<n43:section r:resource="http://129.177.90.166:80/obj/fSection/IEEP2004_Download_VG1" />
</p4:Variable3>
<p4:Variable3 r:about="http://129.177.90.166:80/obj/fVariable/IEEP2004_Download_V3">
<n:complete>true</n:complete>
<s:label>Fine Gael</s:label>
<n:creationDate>2009-11-30 16:13:12.0</n:creationDate>
<n:email>false</n:email>
<n43:name>FG</n43:name>
<n43:study r:resource="http://129.177.90.166:80/obj/fStudy/IEEP2004_Download" />
<n42:numCats>0</n42:numCats>
<n43:isKey>false</n43:isKey>
<n43:isWeight>false</n43:isWeight>
<n43:noInvalidResponses>0</n43:noInvalidResponses>
<n43:decimalPlaces>0</n43:decimalPlaces>
<n43:valRangeMax>494412.0</n43:valRangeMax>
<n43:valRangeMin>90749.0</n43:valRangeMin>
<n43:intervl>contin</n43:intervl>
<n43:format>numeric</n43:format>
<n43:formatSchema>other</n43:formatSchema>
<n43:varID>V3</n43:varID>
<n43:noValidResponses>5</n43:noValidResponses>
<n43:meanValue>197764.8</n43:meanValue>
<n43:maxValue>494412.0</n43:maxValue>
<n43:minValue>90749.0</n43:minValue>
<n43:stdValue>169729.127</n43:stdValue>
<n43:position>3</n43:position>
<n43:sections r:resource="http://129.177.90.166:80/obj/fVariable/IEEP2004_Download_V3@sections" />
<n43:measures r:resource="http://129.177.90.166:80/obj/fVariable/IEEP2004_Download_V3@measures" />
<n43:statistics r:resource="http://129.177.90.166:80/obj/fVariable/IEEP2004_Download_V3@statistics" />
<n43:datafile r:resource="http://129.177.90.166:80/obj/fDatafile/IEEP2004_Download_F1" />
<n43:groups r:resource="http://129.177.90.166:80/obj/fVariable/IEEP2004_Download_V3@groups" />
<n43:factsheets r:resource="http://129.177.90.166:80/obj/fVariable/IEEP2004_Download_V3@factsheets" />
<n43:tables r:resource="http://129.177.90.166:80/obj/fVariable/IEEP2004_Download_V3@tables" />
<n43:weightVariables r:resource="http://129.177.90.166:80/obj/fVariable/IEEP2004_Download_V3@weightVariables" />
<n43:section r:resource="http://129.177.90.166:80/obj/fSection/IEEP2004_Download_VG1" />
</p4:Variable3>
<p4:Variable3 r:about="http://129.177.90.166:80/obj/fVariable/IEEP2004_Download_V4">
<n:complete>true</n:complete>
<s:label>Fianna Fáil</s:label>
<n:creationDate>2009-11-30 16:13:12.0</n:creationDate>
<n:email>false</n:email>
<n43:name>FF</n43:name>
<n43:study r:resource="http://129.177.90.166:80/obj/fStudy/IEEP2004_Download" />
<n42:numCats>0</n42:numCats>
<n43:isKey>false</n43:isKey>
<n43:isWeight>false</n43:isWeight>
<n43:noInvalidResponses>0</n43:noInvalidResponses>
<n43:decimalPlaces>0</n43:decimalPlaces>
<n43:valRangeMax>524504.0</n43:valRangeMax>
<n43:valRangeMin>97950.0</n43:valRangeMin>
<n43:intervl>contin</n43:intervl>
<n43:format>numeric</n43:format>
<n43:formatSchema>other</n43:formatSchema>
<n43:varID>V4</n43:varID>
<n43:noValidResponses>5</n43:noValidResponses>
<n43:meanValue>209801.6</n43:meanValue>
<n43:maxValue>524504.0</n43:maxValue>
<n43:minValue>97950.0</n43:minValue>
<n43:stdValue>180312.63</n43:stdValue>
<n43:position>4</n43:position>
<n43:sections r:resource="http://129.177.90.166:80/obj/fVariable/IEEP2004_Download_V4@sections" />
<n43:measures r:resource="http://129.177.90.166:80/obj/fVariable/IEEP2004_Download_V4@measures" />
<n43:statistics r:resource="http://129.177.90.166:80/obj/fVariable/IEEP2004_Download_V4@statistics" />
<n43:datafile r:resource="http://129.177.90.166:80/obj/fDatafile/IEEP2004_Download_F1" />
<n43:groups r:resource="http://129.177.90.166:80/obj/fVariable/IEEP2004_Download_V4@groups" />
<n43:factsheets r:resource="http://129.177.90.166:80/obj/fVariable/IEEP2004_Download_V4@factsheets" />
<n43:tables r:resource="http://129.177.90.166:80/obj/fVariable/IEEP2004_Download_V4@tables" />
<n43:weightVariables r:resource="http://129.177.90.166:80/obj/fVariable/IEEP2004_Download_V4@weightVariables" />
<n43:section r:resource="http://129.177.90.166:80/obj/fSection/IEEP2004_Download_VG1" />
</p4:Variable3>
<p4:Variable3 r:about="http://129.177.90.166:80/obj/fVariable/IEEP2004_Download_V5">
<n:complete>true</n:complete>
<s:label>Labour Party</s:label>
<n:creationDate>2009-11-30 16:13:12.0</n:creationDate>
<n:email>false</n:email>
<n43:name>LP</n43:name>
<n43:study r:resource="http://129.177.90.166:80/obj/fStudy/IEEP2004_Download" />
<n42:numCats>0</n42:numCats>
<n43:isKey>false</n43:isKey>
<n43:isWeight>false</n43:isWeight>
<n43:noInvalidResponses>0</n43:noInvalidResponses>
<n43:decimalPlaces>0</n43:decimalPlaces>
<n43:valRangeMax>188132.0</n43:valRangeMax>
<n43:valRangeMin>13948.0</n43:valRangeMin>
<n43:intervl>contin</n43:intervl>
<n43:format>numeric</n43:format>
<n43:formatSchema>other</n43:formatSchema>
<n43:varID>V5</n43:varID>
<n43:noValidResponses>5</n43:noValidResponses>
<n43:meanValue>75252.8</n43:meanValue>
<n43:maxValue>188132.0</n43:maxValue>
<n43:minValue>13948.0</n43:minValue>
<n43:stdValue>71075.029</n43:stdValue>
<n43:position>5</n43:position>
<n43:sections r:resource="http://129.177.90.166:80/obj/fVariable/IEEP2004_Download_V5@sections" />
<n43:measures r:resource="http://129.177.90.166:80/obj/fVariable/IEEP2004_Download_V5@measures" />
<n43:statistics r:resource="http://129.177.90.166:80/obj/fVariable/IEEP2004_Download_V5@statistics" />
<n43:datafile r:resource="http://129.177.90.166:80/obj/fDatafile/IEEP2004_Download_F1" />
<n43:groups r:resource="http://129.177.90.166:80/obj/fVariable/IEEP2004_Download_V5@groups" />
<n43:factsheets r:resource="http://129.177.90.166:80/obj/fVariable/IEEP2004_Download_V5@factsheets" />
<n43:tables r:resource="http://129.177.90.166:80/obj/fVariable/IEEP2004_Download_V5@tables" />
<n43:weightVariables r:resource="http://129.177.90.166:80/obj/fVariable/IEEP2004_Download_V5@weightVariables" />
<n43:section r:resource="http://129.177.90.166:80/obj/fSection/IEEP2004_Download_VG1" />
</p4:Variable3>
<p4:Variable3 r:about="http://129.177.90.166:80/obj/fVariable/IEEP2004_Download_V6">
<n:complete>true</n:complete>
<s:label>Sinn Féin</s:label>
<n:creationDate>2009-11-30 16:13:12.0</n:creationDate>
<n:email>false</n:email>
<n43:name>SF</n43:name>
<n43:study r:resource="http://129.177.90.166:80/obj/fStudy/IEEP2004_Download" />
<n42:numCats>0</n42:numCats>
<n43:isKey>false</n43:isKey>
<n43:isWeight>false</n43:isWeight>
<n43:noInvalidResponses>0</n43:noInvalidResponses>
<n43:decimalPlaces>0</n43:decimalPlaces>
<n43:valRangeMax>197715.0</n43:valRangeMax>
<n43:valRangeMin>32643.0</n43:valRangeMin>
<n43:intervl>contin</n43:intervl>
<n43:format>numeric</n43:format>
<n43:formatSchema>other</n43:formatSchema>
<n43:varID>V6</n43:varID>
<n43:noValidResponses>5</n43:noValidResponses>
<n43:meanValue>79086.0</n43:meanValue>
<n43:maxValue>197715.0</n43:maxValue>
<n43:minValue>32643.0</n43:minValue>
<n43:stdValue>67725.722</n43:stdValue>
<n43:position>6</n43:position>
<n43:sections r:resource="http://129.177.90.166:80/obj/fVariable/IEEP2004_Download_V6@sections" />
<n43:measures r:resource="http://129.177.90.166:80/obj/fVariable/IEEP2004_Download_V6@measures" />
<n43:statistics r:resource="http://129.177.90.166:80/obj/fVariable/IEEP2004_Download_V6@statistics" />
<n43:datafile r:resource="http://129.177.90.166:80/obj/fDatafile/IEEP2004_Download_F1" />
<n43:groups r:resource="http://129.177.90.166:80/obj/fVariable/IEEP2004_Download_V6@groups" />
<n43:factsheets r:resource="http://129.177.90.166:80/obj/fVariable/IEEP2004_Download_V6@factsheets" />
<n43:tables r:resource="http://129.177.90.166:80/obj/fVariable/IEEP2004_Download_V6@tables" />
<n43:weightVariables r:resource="http://129.177.90.166:80/obj/fVariable/IEEP2004_Download_V6@weightVariables" />
<n43:section r:resource="http://129.177.90.166:80/obj/fSection/IEEP2004_Download_VG1" />
</p4:Variable3>
<p4:Variable3 r:about="http://129.177.90.166:80/obj/fVariable/IEEP2004_Download_V7">
<n:complete>true</n:complete>
<s:label>Green Party</s:label>
<n:creationDate>2009-11-30 16:13:12.0</n:creationDate>
<n:email>false</n:email>
<n43:name>GP</n43:name>
<n43:study r:resource="http://129.177.90.166:80/obj/fStudy/IEEP2004_Download" />
<n42:numCats>0</n42:numCats>
<n43:isKey>false</n43:isKey>
<n43:isWeight>false</n43:isWeight>
<n43:noInvalidResponses>0</n43:noInvalidResponses>
<n43:decimalPlaces>0</n43:decimalPlaces>
<n43:valRangeMax>76917.0</n43:valRangeMax>
<n43:valRangeMin>0.0</n43:valRangeMin>
<n43:intervl>contin</n43:intervl>
<n43:format>numeric</n43:format>
<n43:formatSchema>other</n43:formatSchema>
<n43:varID>V7</n43:varID>
<n43:noValidResponses>5</n43:noValidResponses>
<n43:meanValue>30766.8</n43:meanValue>
<n43:maxValue>76917.0</n43:maxValue>
<n43:minValue>0.0</n43:minValue>
<n43:stdValue>29966.221</n43:stdValue>
<n43:position>7</n43:position>
<n43:sections r:resource="http://129.177.90.166:80/obj/fVariable/IEEP2004_Download_V7@sections" />
<n43:measures r:resource="http://129.177.90.166:80/obj/fVariable/IEEP2004_Download_V7@measures" />
<n43:statistics r:resource="http://129.177.90.166:80/obj/fVariable/IEEP2004_Download_V7@statistics" />
<n43:datafile r:resource="http://129.177.90.166:80/obj/fDatafile/IEEP2004_Download_F1" />
<n43:groups r:resource="http://129.177.90.166:80/obj/fVariable/IEEP2004_Download_V7@groups" />
<n43:factsheets r:resource="http://129.177.90.166:80/obj/fVariable/IEEP2004_Download_V7@factsheets" />
<n43:tables r:resource="http://129.177.90.166:80/obj/fVariable/IEEP2004_Download_V7@tables" />
<n43:weightVariables r:resource="http://129.177.90.166:80/obj/fVariable/IEEP2004_Download_V7@weightVariables" />
<n43:section r:resource="http://129.177.90.166:80/obj/fSection/IEEP2004_Download_VG1" />
</p4:Variable3>
<p4:Variable3 r:about="http://129.177.90.166:80/obj/fVariable/IEEP2004_Download_V8">
<n:complete>true</n:complete>
<s:label>Independents/ others</s:label>
<n:creationDate>2009-11-30 16:13:12.0</n:creationDate>
<n:email>false</n:email>
<n43:name>Ind</n43:name>
<n43:study r:resource="http://129.177.90.166:80/obj/fStudy/IEEP2004_Download" />
<n42:numCats>0</n42:numCats>
<n43:isKey>false</n43:isKey>
<n43:isWeight>false</n43:isWeight>
<n43:noInvalidResponses>0</n43:noInvalidResponses>
<n43:decimalPlaces>0</n43:decimalPlaces>
<n43:valRangeMax>299088.0</n43:valRangeMax>
<n43:valRangeMin>31668.0</n43:valRangeMin>
<n43:intervl>contin</n43:intervl>
<n43:format>numeric</n43:format>
<n43:formatSchema>other</n43:formatSchema>
<n43:varID>V8</n43:varID>
<n43:noValidResponses>5</n43:noValidResponses>
<n43:meanValue>119635.2</n43:meanValue>
<n43:maxValue>299088.0</n43:maxValue>
<n43:minValue>31668.0</n43:minValue>
<n43:stdValue>108449.267</n43:stdValue>
<n43:position>8</n43:position>
<n43:sections r:resource="http://129.177.90.166:80/obj/fVariable/IEEP2004_Download_V8@sections" />
<n43:measures r:resource="http://129.177.90.166:80/obj/fVariable/IEEP2004_Download_V8@measures" />
<n43:statistics r:resource="http://129.177.90.166:80/obj/fVariable/IEEP2004_Download_V8@statistics" />
<n43:datafile r:resource="http://129.177.90.166:80/obj/fDatafile/IEEP2004_Download_F1" />
<n43:groups r:resource="http://129.177.90.166:80/obj/fVariable/IEEP2004_Download_V8@groups" />
<n43:factsheets r:resource="http://129.177.90.166:80/obj/fVariable/IEEP2004_Download_V8@factsheets" />
<n43:tables r:resource="http://129.177.90.166:80/obj/fVariable/IEEP2004_Download_V8@tables" />
<n43:weightVariables r:resource="http://129.177.90.166:80/obj/fVariable/IEEP2004_Download_V8@weightVariables" />
<n43:section r:resource="http://129.177.90.166:80/obj/fSection/IEEP2004_Download_VG1" />
</p4:Variable3>
<p4:Variable3 r:about="http://129.177.90.166:80/obj/fVariable/IEEP2004_Download_V9">
<n:complete>true</n:complete>
<s:label>Electorate</s:label>
<n:creationDate>2009-11-30 16:13:12.0</n:creationDate>
<n:email>false</n:email>
<n43:name>Electorate</n43:name>
<n43:study r:resource="http://129.177.90.166:80/obj/fStudy/IEEP2004_Download" />
<n42:numCats>0</n42:numCats>
<n43:isKey>false</n43:isKey>
<n43:isWeight>false</n43:isWeight>
<n43:noInvalidResponses>0</n43:noInvalidResponses>
<n43:decimalPlaces>0</n43:decimalPlaces>
<n43:valRangeMax>3143025.0</n43:valRangeMax>
<n43:valRangeMin>688804.0</n43:valRangeMin>
<n43:intervl>contin</n43:intervl>
<n43:format>numeric</n43:format>
<n43:formatSchema>other</n43:formatSchema>
<n43:varID>V9</n43:varID>
<n43:noValidResponses>5</n43:noValidResponses>
<n43:meanValue>1257210.0</n43:meanValue>
<n43:maxValue>3143025.0</n43:maxValue>
<n43:minValue>688804.0</n43:minValue>
<n43:stdValue>1055698.472</n43:stdValue>
<n43:position>9</n43:position>
<n43:sections r:resource="http://129.177.90.166:80/obj/fVariable/IEEP2004_Download_V9@sections" />
<n43:measures r:resource="http://129.177.90.166:80/obj/fVariable/IEEP2004_Download_V9@measures" />
<n43:statistics r:resource="http://129.177.90.166:80/obj/fVariable/IEEP2004_Download_V9@statistics" />
<n43:datafile r:resource="http://129.177.90.166:80/obj/fDatafile/IEEP2004_Download_F1" />
<n43:groups r:resource="http://129.177.90.166:80/obj/fVariable/IEEP2004_Download_V9@groups" />
<n43:factsheets r:resource="http://129.177.90.166:80/obj/fVariable/IEEP2004_Download_V9@factsheets" />
<n43:tables r:resource="http://129.177.90.166:80/obj/fVariable/IEEP2004_Download_V9@tables" />
<n43:weightVariables r:resource="http://129.177.90.166:80/obj/fVariable/IEEP2004_Download_V9@weightVariables" />
<n43:section r:resource="http://129.177.90.166:80/obj/fSection/IEEP2004_Download_VG1" />
</p4:Variable3>
<p4:Variable3 r:about="http://129.177.90.166:80/obj/fVariable/IEEP2004_Download_V10">
<n:complete>true</n:complete>
<s:label>Votes</s:label>
<n:creationDate>2009-11-30 16:13:12.0</n:creationDate>
<n:email>false</n:email>
<n43:name>Votes</n43:name>
<n43:study r:resource="http://129.177.90.166:80/obj/fStudy/IEEP2004_Download" />
<n42:numCats>0</n42:numCats>
<n43:isKey>false</n43:isKey>
<n43:isWeight>false</n43:isWeight>
<n43:noInvalidResponses>0</n43:noInvalidResponses>
<n43:decimalPlaces>0</n43:decimalPlaces>
<n43:valRangeMax>1841335.0</n43:valRangeMax>
<n43:valRangeMin>435136.0</n43:valRangeMin>
<n43:intervl>contin</n43:intervl>
<n43:format>numeric</n43:format>
<n43:formatSchema>other</n43:formatSchema>
<n43:varID>V10</n43:varID>
<n43:noValidResponses>5</n43:noValidResponses>
<n43:meanValue>736534.0</n43:meanValue>
<n43:maxValue>1841335.0</n43:maxValue>
<n43:minValue>435136.0</n43:minValue>
<n43:stdValue>618171.751</n43:stdValue>
<n43:position>10</n43:position>
<n43:sections r:resource="http://129.177.90.166:80/obj/fVariable/IEEP2004_Download_V10@sections" />
<n43:measures r:resource="http://129.177.90.166:80/obj/fVariable/IEEP2004_Download_V10@measures" />
<n43:statistics r:resource="http://129.177.90.166:80/obj/fVariable/IEEP2004_Download_V10@statistics" />
<n43:datafile r:resource="http://129.177.90.166:80/obj/fDatafile/IEEP2004_Download_F1" />
<n43:groups r:resource="http://129.177.90.166:80/obj/fVariable/IEEP2004_Download_V10@groups" />
<n43:factsheets r:resource="http://129.177.90.166:80/obj/fVariable/IEEP2004_Download_V10@factsheets" />
<n43:tables r:resource="http://129.177.90.166:80/obj/fVariable/IEEP2004_Download_V10@tables" />
<n43:weightVariables r:resource="http://129.177.90.166:80/obj/fVariable/IEEP2004_Download_V10@weightVariables" />
<n43:section r:resource="http://129.177.90.166:80/obj/fSection/IEEP2004_Download_VG1" />
</p4:Variable3>
<p4:Variable3 r:about="http://129.177.90.166:80/obj/fVariable/IEEP2004_Download_V11">
<n:complete>true</n:complete>
<s:label>Valid votes</s:label>
<n:creationDate>2009-11-30 16:13:12.0</n:creationDate>
<n:email>false</n:email>
<n43:name>Validvotes</n43:name>
<n43:study r:resource="http://129.177.90.166:80/obj/fStudy/IEEP2004_Download" />
<n42:numCats>0</n42:numCats>
<n43:isKey>false</n43:isKey>
<n43:isWeight>false</n43:isWeight>
<n43:noInvalidResponses>0</n43:noInvalidResponses>
<n43:decimalPlaces>0</n43:decimalPlaces>
<n43:valRangeMax>1780768.0</n43:valRangeMax>
<n43:valRangeMin>421423.0</n43:valRangeMin>
<n43:intervl>contin</n43:intervl>
<n43:format>numeric</n43:format>
<n43:formatSchema>other</n43:formatSchema>
<n43:varID>V11</n43:varID>
<n43:noValidResponses>5</n43:noValidResponses>
<n43:meanValue>712307.2</n43:meanValue>
<n43:maxValue>1780768.0</n43:maxValue>
<n43:minValue>421423.0</n43:minValue>
<n43:stdValue>597852.216</n43:stdValue>
<n43:position>11</n43:position>
<n43:sections r:resource="http://129.177.90.166:80/obj/fVariable/IEEP2004_Download_V11@sections" />
<n43:measures r:resource="http://129.177.90.166:80/obj/fVariable/IEEP2004_Download_V11@measures" />
<n43:statistics r:resource="http://129.177.90.166:80/obj/fVariable/IEEP2004_Download_V11@statistics" />
<n43:datafile r:resource="http://129.177.90.166:80/obj/fDatafile/IEEP2004_Download_F1" />
<n43:groups r:resource="http://129.177.90.166:80/obj/fVariable/IEEP2004_Download_V11@groups" />
<n43:factsheets r:resource="http://129.177.90.166:80/obj/fVariable/IEEP2004_Download_V11@factsheets" />
<n43:tables r:resource="http://129.177.90.166:80/obj/fVariable/IEEP2004_Download_V11@tables" />
<n43:weightVariables r:resource="http://129.177.90.166:80/obj/fVariable/IEEP2004_Download_V11@weightVariables" />
<n43:section r:resource="http://129.177.90.166:80/obj/fSection/IEEP2004_Download_VG1" />
</p4:Variable3>
<p4:Variable3 r:about="http://129.177.90.166:80/obj/fVariable/IEEP2004_Download_V12">
<n:complete>true</n:complete>
<s:label>Invalid votes</s:label>
<n:creationDate>2009-11-30 16:13:12.0</n:creationDate>
<n:email>false</n:email>
<n43:name>Invalidvotes</n43:name>
<n43:study r:resource="http://129.177.90.166:80/obj/fStudy/IEEP2004_Download" />
<n42:numCats>0</n42:numCats>
<n43:isKey>false</n43:isKey>
<n43:isWeight>false</n43:isWeight>
<n43:noInvalidResponses>0</n43:noInvalidResponses>
<n43:decimalPlaces>0</n43:decimalPlaces>
<n43:valRangeMax>60567.0</n43:valRangeMax>
<n43:valRangeMin>13239.0</n43:valRangeMin>
<n43:intervl>contin</n43:intervl>
<n43:format>numeric</n43:format>
<n43:formatSchema>other</n43:formatSchema>
<n43:varID>V12</n43:varID>
<n43:noValidResponses>5</n43:noValidResponses>
<n43:meanValue>24226.8</n43:meanValue>
<n43:maxValue>60567.0</n43:maxValue>
<n43:minValue>13239.0</n43:minValue>
<n43:stdValue>20424.434</n43:stdValue>
<n43:position>12</n43:position>
<n43:sections r:resource="http://129.177.90.166:80/obj/fVariable/IEEP2004_Download_V12@sections" />
<n43:measures r:resource="http://129.177.90.166:80/obj/fVariable/IEEP2004_Download_V12@measures" />
<n43:statistics r:resource="http://129.177.90.166:80/obj/fVariable/IEEP2004_Download_V12@statistics" />
<n43:datafile r:resource="http://129.177.90.166:80/obj/fDatafile/IEEP2004_Download_F1" />
<n43:groups r:resource="http://129.177.90.166:80/obj/fVariable/IEEP2004_Download_V12@groups" />
<n43:factsheets r:resource="http://129.177.90.166:80/obj/fVariable/IEEP2004_Download_V12@factsheets" />
<n43:tables r:resource="http://129.177.90.166:80/obj/fVariable/IEEP2004_Download_V12@tables" />
<n43:weightVariables r:resource="http://129.177.90.166:80/obj/fVariable/IEEP2004_Download_V12@weightVariables" />
<n43:section r:resource="http://129.177.90.166:80/obj/fSection/IEEP2004_Download_VG1" />
</p4:Variable3>

</r:RDF>